dl_data_analysis/__init__.py
dl_data_analysis/main.py
dl_data_analysis-0.3.0.1.dist-info/METADATA
dl_data_analysis-0.3.0.1.dist-info/WHEEL
dl_data_analysis-0.3.0.1.dist-info/top_level.txt
dl_data_analysis-0.3.0.1.dist-info/RECORD
